netdiag_client/__init__.py
netdiag_client/client.py
netdiag_client/errors.py
netdiag_client/types.py
netdiag_client-1.1.0.dist-info/METADATA
netdiag_client-1.1.0.dist-info/WHEEL
netdiag_client-1.1.0.dist-info/RECORD
