Metadata-Version: 2.4
Name: netdiag-client
Version: 1.1.0
Summary: Official Python client for NetDiag API - network diagnostics (HTTP, DNS, TLS, ping) as a service
Project-URL: Homepage, https://netdiag.dev/
Project-URL: Documentation, https://netdiag.dev/docs/python
Project-URL: Repository, https://github.com/xakpc/netdiag-python
Project-URL: Issues, https://github.com/xakpc/netdiag-python/issues
Author-email: XAKPC Dev Labs <netdiag@xakpc.dev>
License-Expression: MIT
Keywords: connectivity,diagnostics,dns,health-check,http,latency,monitoring,network,ping,tls,uptime
Classifier: Development Status :: 4 - Beta
Classifier: Intended Audience :: Developers
Classifier: License :: OSI Approved :: MIT License
Classifier: Programming Language :: Python :: 3
Classifier: Programming Language :: Python :: 3.10
Classifier: Programming Language :: Python :: 3.11
Classifier: Programming Language :: Python :: 3.12
Classifier: Programming Language :: Python :: 3.13
Classifier: Topic :: System :: Networking :: Monitoring
Classifier: Typing :: Typed
Requires-Python: >=3.10
Requires-Dist: httpx>=0.25.0
Provides-Extra: dev
Requires-Dist: pytest-asyncio>=0.23.0; extra == 'dev'
Requires-Dist: pytest>=8.0.0; extra == 'dev'
